dave_base_extensions/__init__.cp311-win_amd64.pyd
dave_base_extensions/file_parser.cp311-win_amd64.pyd
dave_base_extensions/super_elements.cp311-win_amd64.pyd
dave_base_extensions/super_elements_common.cp311-win_amd64.pyd
dave_base_extensions/super_elements_properties.cp311-win_amd64.pyd
dave_base_extensions/super_nodes.cp311-win_amd64.pyd
dave_base_extensions/gui/__init__.cp311-win_amd64.pyd
dave_base_extensions/gui/visuals.cp311-win_amd64.pyd
dave_base_extensions/gui/editors/__init__.cp311-win_amd64.pyd
dave_base_extensions/gui/editors/node_super_element_editor.cp311-win_amd64.pyd
dave_base_extensions/gui/forms/__init__.cp311-win_amd64.pyd
dave_base_extensions/gui/forms/node_super_element_path.cp311-win_amd64.pyd
dave_base_extensions/gui/forms/resources_rc.cp311-win_amd64.pyd
dave_base_extensions/gui/helpers/__init__.cp311-win_amd64.pyd
dave_base_extensions/gui/helpers/se_property_editor.cp311-win_amd64.pyd
dave_base_extensions-2025.0.9.dist-info/licenses/LICENSE.txt
dave_base_extensions-2025.0.9.dist-info/METADATA
dave_base_extensions-2025.0.9.dist-info/WHEEL
dave_base_extensions-2025.0.9.dist-info/top_level.txt
dave_base_extensions-2025.0.9.dist-info/RECORD
